Changelog.md
LICENSE
teleinforeader/__init__.py
teleinforeader/__main__.py
teleinforeader/database/__init__.py
teleinforeader/database/database_client.py
teleinforeader/io/TeleInfoError.py
teleinforeader/io/__init__.py
teleinforeader/io/serial_client.py
teleinforeader/io/socket_server.py
teleinforeader/model/__init__.py
teleinforeader/model/tele_info_data.py
teleinforeader/util/__init__.py
teleinforeader/util/logger.py
teleinforeader/util/tele_info_helpers.py
teleinforeader-0.1.3.dist-info/entry_points.txt
teleinforeader-0.1.3.dist-info/LICENSE
teleinforeader-0.1.3.dist-info/WHEEL
teleinforeader-0.1.3.dist-info/METADATA
teleinforeader-0.1.3.dist-info/RECORD
