Metadata-Version: 2.1
Name: teleinforeader
Version: 0.1.3
Summary: Application used to read the user data transmitted by Linky meter system (TeleInfo) from Enedis.
Home-page: https://github.com/jlesauce/TeleInfoReader
License: MIT
Keywords: teleinfo,enedis,linky
Author: Julien LE SAUCE
Author-email: julien.lesauce@gmail.com
Requires-Python: >=3.7,<4.0
Classifier: Development Status :: 2 - Pre-Alpha
Classifier: Environment :: Console
Classifier: License :: OSI Approved :: MIT License
Classifier: Operating System :: POSIX :: Linux
Classifier: Programming Language :: Python :: 3
Classifier: Programming Language :: Python :: 3.7
Classifier: Programming Language :: Python :: 3.8
Classifier: Programming Language :: Python :: 3.9
Classifier: Programming Language :: Python :: 3.10
Classifier: Programming Language :: Python :: 3.11
Classifier: Programming Language :: Python :: 3
Classifier: Topic :: Home Automation
Classifier: Topic :: Utilities
Requires-Dist: mariadb (==1.0.7)
Requires-Dist: observable (>=1.0.3,<2.0.0)
Requires-Dist: pyserial (>=3.5,<4.0)
Project-URL: Repository, https://github.com/jlesauce/TeleInfoReader
